huaweicloudsdkiotedge/__init__.py
huaweicloudsdkiotedge/v2/__init__.py
huaweicloudsdkiotedge/v2/iotedge_async_client.py
huaweicloudsdkiotedge/v2/iotedge_client.py
huaweicloudsdkiotedge/v2/model/__init__.py
huaweicloudsdkiotedge/v2/model/access_roma_brief_info.py
huaweicloudsdkiotedge/v2/model/access_roma_info.py
huaweicloudsdkiotedge/v2/model/active_control_rsp_dto.py
huaweicloudsdkiotedge/v2/model/active_standby_config_dto.py
huaweicloudsdkiotedge/v2/model/add_app_configs_templates_request.py
huaweicloudsdkiotedge/v2/model/add_app_configs_templates_response.py
huaweicloudsdkiotedge/v2/model/add_device_request.py
huaweicloudsdkiotedge/v2/model/add_device_request_body.py
huaweicloudsdkiotedge/v2/model/add_device_response.py
huaweicloudsdkiotedge/v2/model/add_general_app_configs_template_request.py
huaweicloudsdkiotedge/v2/model/add_general_app_configs_template_response.py
huaweicloudsdkiotedge/v2/model/add_general_ot_template_request.py
huaweicloudsdkiotedge/v2/model/add_general_ot_template_response.py
huaweicloudsdkiotedge/v2/model/add_ot_templates_request.py
huaweicloudsdkiotedge/v2/model/add_ot_templates_response.py
huaweicloudsdkiotedge/v2/model/auth_ak_sk_info.py
huaweicloudsdkiotedge/v2/model/authorize_na2_nodes_request_dto.py
huaweicloudsdkiotedge/v2/model/base_path_dto.py
huaweicloudsdkiotedge/v2/model/batch_associate_na_to_nodes_request.py
huaweicloudsdkiotedge/v2/model/batch_associate_na_to_nodes_response.py
huaweicloudsdkiotedge/v2/model/batch_confirm_configs_new_request.py
huaweicloudsdkiotedge/v2/model/batch_confirm_configs_new_response.py
huaweicloudsdkiotedge/v2/model/batch_import_config_request_body.py
huaweicloudsdkiotedge/v2/model/batch_import_configs_request.py
huaweicloudsdkiotedge/v2/model/batch_import_configs_request_body.py
huaweicloudsdkiotedge/v2/model/batch_import_configs_response.py
huaweicloudsdkiotedge/v2/model/batch_list_app_configs_templates_request.py
huaweicloudsdkiotedge/v2/model/batch_list_app_configs_templates_response.py
huaweicloudsdkiotedge-3.1.184.dist-info/METADATA
huaweicloudsdkiotedge-3.1.184.dist-info/WHEEL
huaweicloudsdkiotedge-3.1.184.dist-info/licenses/LICENSE
huaweicloudsdkiotedge-3.1.184.dist-info/RECORD
